Pile/__init__.py
Pile/datasets.py
Pile/utils.py
the_nordic_pile-0.0.2.dist-info/LICENSE
the_nordic_pile-0.0.2.dist-info/METADATA
the_nordic_pile-0.0.2.dist-info/WHEEL
the_nordic_pile-0.0.2.dist-info/top_level.txt
the_nordic_pile-0.0.2.dist-info/RECORD
