Metadata-Version: 2.1
Name: the-nordic-pile
Version: 0.0.2
Summary: The Nordic Pile
Home-page: https://gits-15.sys.kth.se/bmoell/tmh
Author: Ariel Ekgren, Birger Moell
Author-email: <bmoell@kth.se>
License: UNKNOWN
Project-URL: Bug Tracker, https://gits-15.sys.kth.se/bmoell/tmh/issues
Keywords: python,pile,dataset
Platform: UNKNOWN
Classifier: Development Status :: 1 - Planning
Classifier: Intended Audience :: Developers
Classifier: Programming Language :: Python :: 3
Classifier: Operating System :: Unix
Classifier: Operating System :: MacOS :: MacOS X
Classifier: Operating System :: Microsoft :: Windows
License-File: LICENSE
Requires-Dist: transformers
